mobility/__init__.py
mobility/carbon_computation.py
mobility/coordonnees_communes.py
mobility/get_insee_data.py
mobility/get_survey_data.py
mobility/radiation_departments.py
mobility/radiation_model.py
mobility/safe_sample.py
mobility/trip_sampler.py
mobility/parsers/__init__.py
mobility/parsers/ademe_base_carbone.py
mobility/parsers/communes.py
mobility/parsers/emp_2019.py
mobility/parsers/entd_2008.py
mobility/parsers/job_active_population.py
mobility/parsers/permanent_db_facilities.py
mobility/parsers/work_home_flows.py
mobility_tools-0.1.dist-info/LICENSE
mobility_tools-0.1.dist-info/METADATA
mobility_tools-0.1.dist-info/WHEEL
mobility_tools-0.1.dist-info/top_level.txt
mobility_tools-0.1.dist-info/RECORD
